wikijspy_ext/__init__.py
wikijspy_ext/utils.py
wikijspy_ext-0.0.3.dist-info/METADATA
wikijspy_ext-0.0.3.dist-info/WHEEL
wikijspy_ext-0.0.3.dist-info/top_level.txt
wikijspy_ext-0.0.3.dist-info/RECORD
