Metadata-Version: 2.1
Name: wikijspy-ext
Version: 0.0.3
Summary: A extension package for the wikijspy api wrapper
Author: WERTBON1789
Author-email: jan210404@gmx.de
License: LICENSE
Platform: UNKNOWN
Requires-Dist: wikijspy
